JiagouZhengjiZhidao/README.md
JiagouZhengjiZhidao/__init__.py
JiagouZhengjiZhidao/__main__.py
JiagouZhengjiZhidao/file.epub
JiagouZhengjiZhidao/index.html
JiagouZhengjiZhidao/css/__init__.py
JiagouZhengjiZhidao/css/annotations.css
JiagouZhengjiZhidao/css/main.css
JiagouZhengjiZhidao/css/normalize.css
JiagouZhengjiZhidao/css/popup.css
JiagouZhengjiZhidao/font/__init__.py
JiagouZhengjiZhidao/font/fontello.eot
JiagouZhengjiZhidao/font/fontello.svg
JiagouZhengjiZhidao/font/fontello.ttf
JiagouZhengjiZhidao/font/fontello.woff
JiagouZhengjiZhidao/img/__init__.py
JiagouZhengjiZhidao/img/annotator-glyph-sprite.png
JiagouZhengjiZhidao/img/annotator-icon-sprite.png
JiagouZhengjiZhidao/img/apple-touch-icon.png
JiagouZhengjiZhidao/img/cancelfullscreen.png
JiagouZhengjiZhidao/img/close.png
JiagouZhengjiZhidao/img/fullscreen.png
JiagouZhengjiZhidao/img/loader.gif
JiagouZhengjiZhidao/img/menu-icon.png
JiagouZhengjiZhidao/img/save.png
JiagouZhengjiZhidao/img/saved.png
JiagouZhengjiZhidao/img/settings-s.png
JiagouZhengjiZhidao/img/settings.png
JiagouZhengjiZhidao/img/star.png
JiagouZhengjiZhidao/js/__init__.py
JiagouZhengjiZhidao/js/epub.js
JiagouZhengjiZhidao/js/epub.min.js
JiagouZhengjiZhidao/js/epub.min.map
JiagouZhengjiZhidao/js/hooks.min.js
JiagouZhengjiZhidao/js/hooks.min.map
JiagouZhengjiZhidao/js/reader.js
JiagouZhengjiZhidao/js/reader.js.map
JiagouZhengjiZhidao/js/reader.min.js
JiagouZhengjiZhidao/js/reader.min.map
JiagouZhengjiZhidao/js/hooks/__init__.py
JiagouZhengjiZhidao/js/hooks/extensions/__init__.py
JiagouZhengjiZhidao/js/hooks/extensions/highlight.js
JiagouZhengjiZhidao/js/libs/__init__.py
JiagouZhengjiZhidao/js/libs/jquery.min.js
JiagouZhengjiZhidao/js/libs/localforage.min.js
JiagouZhengjiZhidao/js/libs/screenfull.js
JiagouZhengjiZhidao/js/libs/screenfull.min.js
JiagouZhengjiZhidao/js/libs/zip.min.js
JiagouZhengjiZhidao/js/plugins/__init__.py
JiagouZhengjiZhidao/js/plugins/hypothesis.js
JiagouZhengjiZhidao/js/plugins/search.js
jiagou_zhengji_zhidao-2024.3.4.0.dist-info/METADATA
jiagou_zhengji_zhidao-2024.3.4.0.dist-info/WHEEL
jiagou_zhengji_zhidao-2024.3.4.0.dist-info/entry_points.txt
jiagou_zhengji_zhidao-2024.3.4.0.dist-info/top_level.txt
jiagou_zhengji_zhidao-2024.3.4.0.dist-info/RECORD
